FMA_BLOCK/FMAWriteBuffer.vhd
library IEEE;
use IEEE.STD_LOGIC_1164.ALL;
use IEEE.NUMERIC_STD.ALL;


entity FMAWriteBuffer is 
generic(
    FMA_NUM: integer := 3;
    WORD_LENGTH: integer := 16; -- length of words 
    LINE_LENGTH: integer := 96 -- ie, 6 words that the line can accept (for 3 FMA blocks, line is flushed once every 2 cycles )
);

port(
    clk: in std_logic;
    rst: in std_logic;
    -- inputs
    -- fma_out: a string of length WORD_LENGTH*FMA_NUM that contains the result of product
    -- fma_valid_out: a FMA_NUM of booleans that defines 
    fma_out: in std_logic_vector(WORD_LENGTH*FMA_NUM-1 downto 0); -- is -1 cprrect? to check
    fma_valid_out: in std_logic_vector(FMA_NUM-1 downto 0);

    --outputs
    line_out: out std_logic_vector(3*WORD_LENGTH*FMA_NUM - 1 downto 0);
    line_valid: out std_logic

);
end FMAWriteBuffer;

architecture Behavioral of FMAWriteBuffer is

    -- function to define the line WRITE_BUFFER_OUTPUT
    -- phrase = FMA_NUM * WORD_LENGTH (a long string of )
    function WRITE_BUFFER_OUTPUT(
        FMA_ID  : integer;
        PHRASE  : integer
    ) return integer is
    begin
        return (phrase * fma_num * word_length) + (fma_id * word_length);
    end function;

    signal phrase_in        : integer range 0 to 3 := 0;
    signal increment_phrase : std_logic;
    signal line_out_reg     : std_logic_vector(3*WORD_LENGTH*FMA_NUM - 1 downto 0) := (others => '0');
    signal line_valid_reg   : std_logic := '0';

    -- main idea: we get the fma_output data (results of fma blocks)
    -- and place them into the line out output as a single string of data to feed the frame buffer with
    begin

        -- MUX increment_phrase to correct default output
        increment_phrase <= '1' when unsigned(fma_valid_out)/= 0  else '0'; -- unsigned converts std_logic_vector to numeric

        process(clk)
        begin
            if rising_edge(clk) then
                if(rst = '1') then
                    line_valid <= '0';
                    phrase_in <= 0;
                    line_out <= (others => '0');
                else 
                    if (phrase_in < 3) then
                        if(increment_phrase = '1') then
                            for i in 0 to FMA_NUM-1 loop
                                line_out(  -- to check logic
                                        WRITE_BUFFER_OUTPUT(i, phrase_in) + WORD_LENGTH - 1 downto
                                        WRITE_BUFFER_OUTPUT(i, phrase_in)
                                ) <= fma_out((i+1)*WORD_LENGTH - 1 downto i*WORD_LENGTH);
                            end loop;

                            phrase_in <= phrase_in + 1;

                            if phrase_in = 2 then
                                line_valid_reg <= '1';
                            else
                                line_valid_reg <= '0';
                            end if;
                        end if;
                    else 
                        -- Reset for next line
                        phrase_in      <= 0;
                        line_out_reg   <= (others => '0');
                        line_valid_reg <= '0';
                    end if;
                end if;
                
            end if;
        end process;

end Behavioral;

FMA_BLOCK/FMAWriteBuffer_tb.vhd
library ieee;
use ieee.std_logic_1164.all;
use ieee.numeric_std.all;

entity FMAWriteBuffer_tb is
end FMAWriteBuffer_tb;

architecture sim of FMAWriteBuffer_tb is
    
    constant FMA_NUM: integer := 3;
    constant WORD_LENGTH: integer := 16; -- length of words 
    constant LINE_LENGTH: integer := 96; -- ie, 6 words that the line can accept (for 3 FMA blocks, line is flushed once every 2 cycles )

    -- Clock period
    constant CLK_PERIOD : time := 10 ns; -- 100 MHz

    -- DUT signals
    signal clk: std_logic := '0';
    signal rst: std_logic := '0';

    signal fma_out: std_logic_vector(WORD_LENGTH*FMA_NUM-1 downto 0) := (others => '0');
    signal fma_valid_out: std_logic_vector(FMA_NUM-1 downto 0 ) := (others => '0');

    signal line_out: std_logic_vector(3*WORD_LENGTH*FMA_NUM - 1 downto 0);
    signal line_valid: std_logic := '0';

begin
    -- Instantiate DUT
    FMAWriteBufferEntity: entity work.FMAWriteBuffer
        port map (
            clk => clk,
            rst => rst,
            fma_out => fma_out,
            fma_valid_out => fma_valid_out,
            line_out => line_out,
            line_valid => line_valid
        );

    -- Clock generation
    clk_gen : process
    begin
        while true loop
            clk <= '0';
            wait for CLK_PERIOD/2;
            clk <= '1';
            wait for CLK_PERIOD/2;
        end loop;
    end process;

    -- Stimulus
    stim_proc : process
    begin
        -- Apply reset
        rst <= '1';
        wait for 100 ns;
        rst <= '0';
        wait for 100 ns;

        -- idea: send fma_out array of results (send 3 as FMA_NUM)
        -- then define a temporary fma_valid_out array (actually, define 4 or 5 different types of valids to see what happens)
        -- see what happens on the linout

        -- FIRST TEST
        -- Define a random fma_out hypthetical result string
        -- first batch
        fma_out   <= x"5EAA5EAA5EAA";   -- initialize fma_out
        fma_valid_out <= "101";          -- define whether the fma_blocks are valid or not 
        wait for 50 ns;

        -- second batch 
        fma_out <= x"51AB5EBA2FAA";
        fma_valid_out <= "111";
        wait for 10 us;

        -- End simulation
        wait;
    end process;

end sim;

FMA_BLOCK/FMAWriteBuffer_tb.vcd
$date
  Mon Oct 20 22:00:07 2025
$end
$version
  GHDL v0
$end
$timescale
  1 fs
$end
$scope module standard $end
$upscope $end
$scope module std_logic_1164 $end
$upscope $end
$scope module numeric_std $end
$upscope $end
$scope module fmawritebuffer_tb $end
$var reg 1 ! clk $end
$var reg 1 " rst $end
$var reg 48 # fma_out[47:0] $end
$var reg 3 $ fma_valid_out[2:0] $end
$var reg 144 % line_out[143:0] $end
$var reg 1 & line_valid $end
$scope module fmawritebufferentity $end
$var reg 1 ' clk $end
$var reg 1 ( rst $end
$var reg 48 ) fma_out[47:0] $end
$var reg 3 * fma_valid_out[2:0] $end
$var reg 144 + line_out[143:0] $end
$var reg 1 , line_valid $end
$var integer 32 - phrase_in $end
$var reg 1 . increment_phrase $end
$var reg 144 / line_out_reg[143:0] $end
$var reg 1 0 line_valid_reg $end
$upscope $end
$upscope $end
$enddefinitions $end
#0
0!
1"
b000000000000000000000000000000000000000000000000 #
b000 $
bUUUUUUUUUUUUUUUUUUUUUUUUUUUUUUUUUUUUUUUUUUUUUUUUUUUUUUUUUUUUUUUUUUUUUUUUUUUUUUUUUUUUUUUUUUUUUUUUUUUUUUUUUUUUUUUUUUUUUUUUUUUUUUUUUUUUUUUUUUUUUUUU %
U&
0'
1(
b000000000000000000000000000000000000000000000000 )
b000 *
bUUUUUUUUUUUUUUUUUUUUUUUUUUUUUUUUUUUUUUUUUUUUUUUUUUUUUUUUUUUUUUUUUUUUUUUUUUUUUUUUUUUUUUUUUUUUUUUUUUUUUUUUUUUUUUUUUUUUUUUUUUUUUUUUUUUUUUUUUUUUUUUU +
U,
b0 -
0.
b000000000000000000000000000000000000000000000000000000000000000000000000000000000000000000000000000000000000000000000000000000000000000000000000 /
00
#5000000
1!
b000000000000000000000000000000000000000000000000000000000000000000000000000000000000000000000000000000000000000000000000000000000000000000000000 %
0&
1'
b000000000000000000000000000000000000000000000000000000000000000000000000000000000000000000000000000000000000000000000000000000000000000000000000 +
0,
#10000000
0!
0'
#15000000
1!
1'
#20000000
0!
0'
#25000000
1!
1'
#30000000
0!
0'
#35000000
1!
1'
#40000000
0!
0'
#45000000
1!
1'
#50000000
0!
0'
#55000000
1!
1'
#60000000
0!
0'
#65000000
1!
1'
#70000000
0!
0'
#75000000
1!
1'
#80000000
0!
0'
#85000000
1!
1'
#90000000
0!
0'
#95000000
1!
1'
#100000000
0!
0"
0'
0(
#105000000
1!
1'
#110000000
0!
0'
#115000000
1!
1'
#120000000
0!
0'
#125000000
1!
1'
#130000000
0!
0'
#135000000
1!
1'
#140000000
0!
0'
#145000000
1!
1'
#150000000
0!
0'
#155000000
1!
1'
#160000000
0!
0'
#165000000
1!
1'
#170000000
0!
0'
#175000000
1!
1'
#180000000
0!
0'
#185000000
1!
1'
#190000000
0!
0'
#195000000
1!
1'
#200000000
0!
b010111101010101001011110101010100101111010101010 #
b101 $
0'
b010111101010101001011110101010100101111010101010 )
b101 *
1.
#205000000
1!
b000000000000000000000000000000000000000000000000000000000000000000000000000000000000000000000000010111101010101001011110101010100101111010101010 %
1'
b000000000000000000000000000000000000000000000000000000000000000000000000000000000000000000000000010111101010101001011110101010100101111010101010 +
b1 -
#210000000
0!
0'
#215000000
1!
b000000000000000000000000000000000000000000000000010111101010101001011110101010100101111010101010010111101010101001011110101010100101111010101010 %
1'
b000000000000000000000000000000000000000000000000010111101010101001011110101010100101111010101010010111101010101001011110101010100101111010101010 +
b10 -
#220000000
0!
0'
#225000000
1!
b010111101010101001011110101010100101111010101010010111101010101001011110101010100101111010101010010111101010101001011110101010100101111010101010 %
1'
b010111101010101001011110101010100101111010101010010111101010101001011110101010100101111010101010010111101010101001011110101010100101111010101010 +
b11 -
10
#230000000
0!
0'
#235000000
1!
1'
b0 -
00
#240000000
0!
0'
#245000000
1!
1'
b1 -
#250000000
0!
b010100011010101101011110101110100010111110101010 #
b111 $
0'
b010100011010101101011110101110100010111110101010 )
b111 *
#255000000
1!
b010111101010101001011110101010100101111010101010010100011010101101011110101110100010111110101010010111101010101001011110101010100101111010101010 %
1'
b010111101010101001011110101010100101111010101010010100011010101101011110101110100010111110101010010111101010101001011110101010100101111010101010 +
b10 -
#260000000
0!
0'
#265000000
1!
b010100011010101101011110101110100010111110101010010100011010101101011110101110100010111110101010010111101010101001011110101010100101111010101010 %
1'
b010100011010101101011110101110100010111110101010010100011010101101011110101110100010111110101010010111101010101001011110101010100101111010101010 +
b11 -
10
#270000000
0!
0'
#275000000
1!
1'
b0 -
00
#280000000
0!
0'
#285000000
1!
b010100011010101101011110101110100010111110101010010100011010101101011110101110100010111110101010010100011010101101011110101110100010111110101010 %
1'
b010100011010101101011110101110100010111110101010010100011010101101011110101110100010111110101010010100011010101101011110101110100010111110101010 +
b1 -
#290000000
0!
0'
#295000000
1!
1'
b10 -
#300000000
0!
0'
#305000000
1!
1'
b11 -
10
#310000000
0!
0'
#315000000
1!
1'
b0 -
00
#320000000
0!
0'
#325000000
1!
1'
b1 -
#330000000
0!
0'
#335000000
1!
1'
b10 -
#340000000
0!
0'
#345000000
1!
1'
b11 -
10
#350000000
0!
0'
#355000000
1!
1'
b0 -
00
#360000000
0!
0'
#365000000
1!
1'
b1 -
#370000000
0!
0'
#375000000
1!
1'
b10 -
#380000000
0!
0'
#385000000
1!
1'
b11 -
10
#390000000
0!
0'
#395000000
1!
1'
b0 -
00
#400000000
0!
0'
#405000000
1!
1'
b1 -
#410000000
0!
0'
#415000000
1!
1'
b10 -
#420000000
0!
0'
#425000000
1!
1'
b11 -
10
#430000000
0!
0'
#435000000
1!
1'
b0 -
00
#440000000
0!
0'
#445000000
1!
1'
b1 -
#450000000
0!
0'
#455000000
1!
1'
b10 -
#460000000
0!
0'
#465000000
1!
1'
b11 -
10
#470000000
0!
0'
#475000000
1!
1'
b0 -
00
#480000000
0!
0'
#485000000
1!
1'
b1 -
#490000000
0!
0'
#495000000
1!
1'
b10 -
#500000000
0!
0'
#505000000
1!
1'
b11 -
10
#510000000
0!
0'
#515000000
1!
1'
b0 -
00
#520000000
0!
0'
#525000000
1!
1'
b1 -
#530000000
0!
0'
#535000000
1!
1'
b10 -
#540000000
0!
0'
#545000000
1!
1'
b11 -
10
#550000000
0!
0'
#555000000
1!
1'
b0 -
00
#560000000
0!
0'
#565000000
1!
1'
b1 -
#570000000
0!
0'
#575000000
1!
1'
b10 -
#580000000
0!
0'
#585000000
1!
1'
b11 -
10
#590000000
0!
0'
#595000000
1!
1'
b0 -
00
#600000000
0!
0'
#605000000
1!
1'
b1 -
#610000000
0!
0'
#615000000
1!
1'
b10 -
#620000000
0!
0'
#625000000
1!
1'
b11 -
10
#630000000
0!
0'
#635000000
1!
1'
b0 -
00
#640000000
0!
0'
#645000000
1!
1'
b1 -
#650000000
0!
0'
#655000000
1!
1'
b10 -
#660000000
0!
0'
#665000000
1!
1'
b11 -
10
#670000000
0!
0'
#675000000
1!
1'
b0 -
00
#680000000
0!
0'
#685000000
1!
1'
b1 -
#690000000
0!
0'
#695000000
1!
1'
b10 -
#700000000
0!
0'
#705000000
1!
1'
b11 -
10
#710000000
0!
0'
#715000000
1!
1'
b0 -
00
#720000000
0!
0'
#725000000
1!
1'
b1 -
#730000000
0!
0'
#735000000
1!
1'
b10 -
#740000000
0!
0'
#745000000
1!
1'
b11 -
10
#750000000
0!
0'
#755000000
1!
1'
b0 -
00
#760000000
0!
0'
#765000000
1!
1'
b1 -
#770000000
0!
0'
#775000000
1!
1'
b10 -
#780000000
0!
0'
#785000000
1!
1'
b11 -
10
#790000000
0!
0'
#795000000
1!
1'
b0 -
00
#800000000
0!
0'
#805000000
1!
1'
b1 -
#810000000
0!
0'
#815000000
1!
1'
b10 -
#820000000
0!
0'
#825000000
1!
1'
b11 -
10
#830000000
0!
0'
#835000000
1!
1'
b0 -
00
#840000000
0!
0'
#845000000
1!
1'
b1 -
#850000000
0!
0'
#855000000
1!
1'
b10 -
#860000000
0!
0'
#865000000
1!
1'
b11 -
10
#870000000
0!
0'
#875000000
1!
1'
b0 -
00
#880000000
0!
0'
#885000000
1!
1'
b1 -
#890000000
0!
0'
#895000000
1!
1'
b10 -
#900000000
0!
0'
#905000000
1!
1'
b11 -
10
#910000000
0!
0'
#915000000
1!
1'
b0 -
00
#920000000
0!
0'
#925000000
1!
1'
b1 -
#930000000
0!
0'
#935000000
1!
1'
b10 -
#940000000
0!
0'
#945000000
1!
1'
b11 -
10
#950000000
0!
0'
#955000000
1!
1'
b0 -
00
#960000000
0!
0'
#965000000
1!
1'
b1 -
#970000000
0!
0'
#975000000
1!
1'
b10 -
#980000000
0!
0'
#985000000
1!
1'
b11 -
10
#990000000
0!
0'
#995000000
1!
1'
b0 -
00
#1000000000
0!
0'
#1005000000
1!
1'
b1 -
#1010000000
0!
0'
#1015000000
1!
1'
b10 -
#1020000000
0!
0'
#1025000000
1!
1'
b11 -
10
#1030000000
0!
0'
#1035000000
1!
1'
b0 -
00
#1040000000
0!
0'
#1045000000
1!
1'
b1 -
#1050000000
0!
0'
#1055000000
1!
1'
b10 -
#1060000000
0!
0'
#1065000000
1!
1'
b11 -
10
#1070000000
0!
0'
#1075000000
1!
1'
b0 -
00
#1080000000
0!
0'
#1085000000
1!
1'
b1 -
#1090000000
0!
0'
#1095000000
1!
1'
b10 -
#1100000000
0!
0'
#1105000000
1!
1'
b11 -
10
#1110000000
0!
0'
#1115000000
1!
1'
b0 -
00
#1120000000
0!
0'
#1125000000
1!
1'
b1 -
#1130000000
0!
0'
#1135000000
1!
1'
b10 -
#1140000000
0!
0'
#1145000000
1!
1'
b11 -
10
#1150000000
0!
0'
#1155000000
1!
1'
b0 -
00
#1160000000
0!
0'
#1165000000
1!
1'
b1 -
#1170000000
0!
0'
#1175000000
1!
1'
b10 -
#1180000000
0!
0'
#1185000000
1!
1'
b11 -
10
#1190000000
0!
0'
#1195000000
1!
1'
b0 -
00
#1200000000
0!
0'
#1205000000
1!
1'
b1 -
#1210000000
0!
0'
#1215000000
1!
1'
b10 -
#1220000000
0!
0'
#1225000000
1!
1'
b11 -
10
#1230000000
0!
0'
#1235000000
1!
1'
b0 -
00
#1240000000
0!
0'
#1245000000
1!
1'
b1 -
#1250000000
0!
0'
#1255000000
1!
1'
b10 -
#1260000000
0!
0'
#1265000000
1!
1'
b11 -
10
#1270000000
0!
0'
#1275000000
1!
1'
b0 -
00
#1280000000
0!
0'
#1285000000
1!
1'
b1 -
#1290000000
0!
0'
#1295000000
1!
1'
b10 -
#1300000000
0!
0'
#1305000000
1!
1'
b11 -
10
#1310000000
0!
0'
#1315000000
1!
1'
b0 -
00
#1320000000
0!
0'
#1325000000
1!
1'
b1 -
#1330000000
0!
0'
#1335000000
1!
1'
b10 -
#1340000000
0!
0'
#1345000000
1!
1'
b11 -
10
#1350000000
0!
0'
#1355000000
1!
1'
b0 -
00
#1360000000
0!
0'
#1365000000
1!
1'
b1 -
#1370000000
0!
0'
#1375000000
1!
1'
b10 -
#1380000000
0!
0'
#1385000000
1!
1'
b11 -
10
#1390000000
0!
0'
#1395000000
1!
1'
b0 -
00
#1400000000
0!
0'
#1405000000
1!
1'
b1 -
#1410000000
0!
0'
#1415000000
1!
1'
b10 -
#1420000000
0!
0'
#1425000000
1!
1'
b11 -
10
#1430000000
0!
0'
#1435000000
1!
1'
b0 -
00
#1440000000
0!
0'
#1445000000
1!
1'
b1 -
#1450000000
0!
0'
#1455000000
1!
1'
b10 -
#1460000000
0!
0'
#1465000000
1!
1'
b11 -
10
#1470000000
0!
0'
#1475000000
1!
1'
b0 -
00
#1480000000
0!
0'
#1485000000
1!
1'
b1 -
#1490000000
0!
0'
#1495000000
1!
1'
b10 -
#1500000000
0!
0'
#1505000000
1!
1'
b11 -
10
#1510000000
0!
0'
#1515000000
1!
1'
b0 -
00
#1520000000
0!
0'
#1525000000
1!
1'
b1 -
#1530000000
0!
0'
#1535000000
1!
1'
b10 -
#1540000000
0!
0'
#1545000000
1!
1'
b11 -
10
#1550000000
0!
0'
#1555000000
1!
1'
b0 -
00
#1560000000
0!
0'
#1565000000
1!
1'
b1 -
#1570000000
0!
0'
#1575000000
1!
1'
b10 -
#1580000000
0!
0'
#1585000000
1!
1'
b11 -
10
#1590000000
0!
0'
#1595000000
1!
1'
b0 -
00
#1600000000
0!
0'
#1605000000
1!
1'
b1 -
#1610000000
0!
0'
#1615000000
1!
1'
b10 -
#1620000000
0!
0'
#1625000000
1!
1'
b11 -
10
#1630000000
0!
0'
#1635000000
1!
1'
b0 -
00
#1640000000
0!
0'
#1645000000
1!
1'
b1 -
#1650000000
0!
0'
#1655000000
1!
1'
b10 -
#1660000000
0!
0'
#1665000000
1!
1'
b11 -
10
#1670000000
0!
0'
#1675000000
1!
1'
b0 -
00
#1680000000
0!
0'
#1685000000
1!
1'
b1 -
#1690000000
0!
0'
#1695000000
1!
1'
b10 -
#1700000000
0!
0'
#1705000000
1!
1'
b11 -
10
#1710000000
0!
0'
#1715000000
1!
1'
b0 -
00
#1720000000
0!
0'
#1725000000
1!
1'
b1 -
#1730000000
0!
0'
#1735000000
1!
1'
b10 -
#1740000000
0!
0'
#1745000000
1!
1'
b11 -
10
#1750000000
0!
0'
#1755000000
1!
1'
b0 -
00
#1760000000
0!
0'
#1765000000
1!
1'
b1 -
#1770000000
0!
0'
#1775000000
1!
1'
b10 -
#1780000000
0!
0'
#1785000000
1!
1'
b11 -
10
#1790000000
0!
0'
#1795000000
1!
1'
b0 -
00
#1800000000
0!
0'
#1805000000
1!
1'
b1 -
#1810000000
0!
0'
#1815000000
1!
1'
b10 -
#1820000000
0!
0'
#1825000000
1!
1'
b11 -
10
#1830000000
0!
0'
#1835000000
1!
1'
b0 -
00
#1840000000
0!
0'
#1845000000
1!
1'
b1 -
#1850000000
0!
0'
#1855000000
1!
1'
b10 -
#1860000000
0!
0'
#1865000000
1!
1'
b11 -
10
#1870000000
0!
0'
#1875000000
1!
1'
b0 -
00
#1880000000
0!
0'
#1885000000
1!
1'
b1 -
#1890000000
0!
0'
#1895000000
1!
1'
b10 -
#1900000000
0!
0'
#1905000000
1!
1'
b11 -
10
#1910000000
0!
0'
#1915000000
1!
1'
b0 -
00
#1920000000
0!
0'
#1925000000
1!
1'
b1 -
#1930000000
0!
0'
#1935000000
1!
1'
b10 -
#1940000000
0!
0'
#1945000000
1!
1'
b11 -
10
#1950000000
0!
0'
#1955000000
1!
1'
b0 -
00
#1960000000
0!
0'
#1965000000
1!
1'
b1 -
#1970000000
0!
0'
#1975000000
1!
1'
b10 -
#1980000000
0!
0'
#1985000000
1!
1'
b11 -
10
#1990000000
0!
0'
#1995000000
1!
1'
b0 -
00
#2000000000
0!
0'
#2005000000
1!
1'
b1 -
#2010000000
0!
0'
#2015000000
1!
1'
b10 -
#2020000000
0!
0'
#2025000000
1!
1'
b11 -
10
#2030000000
0!
0'
#2035000000
1!
1'
b0 -
00
#2040000000
0!
0'
#2045000000
1!
1'
b1 -
#2050000000
0!
0'
#2055000000
1!
1'
b10 -
#2060000000
0!
0'
#2065000000
1!
1'
b11 -
10
#2070000000
0!
0'
#2075000000
1!
1'
b0 -
00
#2080000000
0!
0'
#2085000000
1!
1'
b1 -
#2090000000
0!
0'
#2095000000
1!
1'
b10 -
#2100000000
0!
0'
#2105000000
1!
1'
b11 -
10
#2110000000
0!
0'
#2115000000
1!
1'
b0 -
00
#2120000000
0!
0'
#2125000000
1!
1'
b1 -
#2130000000
0!
0'
#2135000000
1!
1'
b10 -
#2140000000
0!
0'
#2145000000
1!
1'
b11 -
10
#2150000000
0!
0'
#2155000000
1!
1'
b0 -
00
#2160000000
0!
0'
#2165000000
1!
1'
b1 -
#2170000000
0!
0'
#2175000000
1!
1'
b10 -
#2180000000
0!
0'
#2185000000
1!
1'
b11 -
10
#2190000000
0!
0'
#2195000000
1!
1'
b0 -
00
#2200000000
0!
0'
#2205000000
1!
1'
b1 -
#2210000000
0!
0'
#2215000000
1!
1'
b10 -
#2220000000
0!
0'
#2225000000
1!
1'
b11 -
10
#2230000000
0!
0'
#2235000000
1!
1'
b0 -
00
#2240000000
0!
0'
#2245000000
1!
1'
b1 -
#2250000000
0!
0'
#2255000000
1!
1'
b10 -
#2260000000
0!
0'
#2265000000
1!
1'
b11 -
10
#2270000000
0!
0'
#2275000000
1!
1'
b0 -
00
#2280000000
0!
0'
#2285000000
1!
1'
b1 -
#2290000000
0!
0'
#2295000000
1!
1'
b10 -
#2300000000
0!
0'
#2305000000
1!
1'
b11 -
10
#2310000000
0!
0'
#2315000000
1!
1'
b0 -
00
#2320000000
0!
0'
#2325000000
1!
1'
b1 -
#2330000000
0!
0'
#2335000000
1!
1'
b10 -
#2340000000
0!
0'
#2345000000
1!
1'
b11 -
10
#2350000000
0!
0'
#2355000000
1!
1'
b0 -
00
#2360000000
0!
0'
#2365000000
1!
1'
b1 -
#2370000000
0!
0'
#2375000000
1!
1'
b10 -
#2380000000
0!
0'
#2385000000
1!
1'
b11 -
10
#2390000000
0!
0'
#2395000000
1!
1'
b0 -
00
#2400000000
0!
0'
#2405000000
1!
1'
b1 -
#2410000000
0!
0'
#2415000000
1!
1'
b10 -
#2420000000
0!
0'
#2425000000
1!
1'
b11 -
10
#2430000000
0!
0'
#2435000000
1!
1'
b0 -
00
#2440000000
0!
0'
#2445000000
1!
1'
b1 -
#2450000000
0!
0'
#2455000000
1!
1'
b10 -
#2460000000
0!
0'
#2465000000
1!
1'
b11 -
10
#2470000000
0!
0'
#2475000000
1!
1'
b0 -
00
#2480000000
0!
0'
#2485000000
1!
1'
b1 -
#2490000000
0!
0'
#2495000000
1!
1'
b10 -
#2500000000
0!
0'
#2505000000
1!
1'
b11 -
10
#2510000000
0!
0'
#2515000000
1!
1'
b0 -
00
#2520000000
0!
0'
#2525000000
1!
1'
b1 -
#2530000000
0!
0'
#2535000000
1!
1'
b10 -
#2540000000
0!
0'
#2545000000
1!
1'
b11 -
10
#2550000000
0!
0'
#2555000000
1!
1'
b0 -
00
#2560000000
0!
0'
#2565000000
1!
1'
b1 -
#2570000000
0!
0'
#2575000000
1!
1'
b10 -
#2580000000
0!
0'
#2585000000
1!
1'
b11 -
10
#2590000000
0!
0'
#2595000000
1!
1'
b0 -
00
#2600000000
0!
0'
#2605000000
1!
1'
b1 -
#2610000000
0!
0'
#2615000000
1!
1'
b10 -
#2620000000
0!
0'
#2625000000
1!
1'
b11 -
10
#2630000000
0!
0'
#2635000000
1!
1'
b0 -
00
#2640000000
0!
0'
#2645000000
1!
1'
b1 -
#2650000000
0!
0'
#2655000000
1!
1'
b10 -
#2660000000
0!
0'
#2665000000
1!
1'
b11 -
10
#2670000000
0!
0'
#2675000000
1!
1'
b0 -
00
#2680000000
0!
0'
#2685000000
1!
1'
b1 -
#2690000000
0!
0'
#2695000000
1!
1'
b10 -
#2700000000
0!
0'
#2705000000
1!
1'
b11 -
10
#2710000000
0!
0'
#2715000000
1!
1'
b0 -
00
#2720000000
0!
0'
#2725000000
1!
1'
b1 -
#2730000000
0!
0'
#2735000000
1!
1'
b10 -
#2740000000
0!
0'
#2745000000
1!
1'
b11 -
10
#2750000000
0!
0'
#2755000000
1!
1'
b0 -
00
#2760000000
0!
0'
#2765000000
1!
1'
b1 -
#2770000000
0!
0'
#2775000000
1!
1'
b10 -
#2780000000
0!
0'
#2785000000
1!
1'
b11 -
10
#2790000000
0!
0'
#2795000000
1!
1'
b0 -
00
#2800000000
0!
0'
#2805000000
1!
1'
b1 -
#2810000000
0!
0'
#2815000000
1!
1'
b10 -
#2820000000
0!
0'
#2825000000
1!
1'
b11 -
10
#2830000000
0!
0'
#2835000000
1!
1'
b0 -
00
#2840000000
0!
0'
#2845000000
1!
1'
b1 -
#2850000000
0!
0'
#2855000000
1!
1'
b10 -
#2860000000
0!
0'
#2865000000
1!
1'
b11 -
10
#2870000000
0!
0'
#2875000000
1!
1'
b0 -
00
#2880000000
0!
0'
#2885000000
1!
1'
b1 -
#2890000000
0!
0'
#2895000000
1!
1'
b10 -
#2900000000
0!
0'
#2905000000
1!
1'
b11 -
10
#2910000000
0!
0'
#2915000000
1!
1'
b0 -
00
#2920000000
0!
0'
#2925000000
1!
1'
b1 -
#2930000000
0!
0'
#2935000000
1!
1'
b10 -
#2940000000
0!
0'
#2945000000
1!
1'
b11 -
10
#2950000000
0!
0'
#2955000000
1!
1'
b0 -
00
#2960000000
0!
0'
#2965000000
1!
1'
b1 -
#2970000000
0!
0'
#2975000000
1!
1'
b10 -
#2980000000
0!
0'
#2985000000
1!
1'
b11 -
10
#2990000000
0!
0'
#2995000000
1!
1'
b0 -
00
#3000000000
0!
0'
#3005000000
1!
1'
b1 -
#3010000000
0!
0'
#3015000000
1!
1'
b10 -
#3020000000
0!
0'
#3025000000
1!
1'
b11 -
10
#3030000000
0!
0'
#3035000000
1!
1'
b0 -
00
#3040000000
0!
0'
#3045000000
1!
1'
b1 -
#3050000000
0!
0'
#3055000000
1!
1'
b10 -
#3060000000
0!
0'
#3065000000
1!
1'
b11 -
10
#3070000000
0!
0'
#3075000000
1!
1'
b0 -
00
#3080000000
0!
0'
#3085000000
1!
1'
b1 -
#3090000000
0!
0'
#3095000000
1!
1'
b10 -
#3100000000
0!
0'
#3105000000
1!
1'
b11 -
10
#3110000000
0!
0'
#3115000000
1!
1'
b0 -
00
#3120000000
0!
0'
#3125000000
1!
1'
b1 -
#3130000000
0!
0'
#3135000000
1!
1'
b10 -
#3140000000
0!
0'
#3145000000
1!
1'
b11 -
10
#3150000000
0!
0'
#3155000000
1!
1'
b0 -
00
#3160000000
0!
0'
#3165000000
1!
1'
b1 -
#3170000000
0!
0'
#3175000000
1!
1'
b10 -
#3180000000
0!
0'
#3185000000
1!
1'
b11 -
10
#3190000000
0!
0'
#3195000000
1!
1'
b0 -
00
#3200000000
0!
0'
#3205000000
1!
1'
b1 -
#3210000000
0!
0'
#3215000000
1!
1'
b10 -
#3220000000
0!
0'
#3225000000
1!
1'
b11 -
10
#3230000000
0!
0'
#3235000000
1!
1'
b0 -
00
#3240000000
0!
0'
#3245000000
1!
1'
b1 -
#3250000000
0!
0'
#3255000000
1!
1'
b10 -
#3260000000
0!
0'
#3265000000
1!
1'
b11 -
10
#3270000000
0!
0'
#3275000000
1!
1'
b0 -
00
#3280000000
0!
0'
#3285000000
1!
1'
b1 -
#3290000000
0!
0'
#3295000000
1!
1'
b10 -
#3300000000
0!
0'
#3305000000
1!
1'
b11 -
10
#3310000000
0!
0'
#3315000000
1!
1'
b0 -
00
#3320000000
0!
0'
#3325000000
1!
1'
b1 -
#3330000000
0!
0'
#3335000000
1!
1'
b10 -
#3340000000
0!
0'
#3345000000
1!
1'
b11 -
10
#3350000000
0!
0'
#3355000000
1!
1'
b0 -
00
#3360000000
0!
0'
#3365000000
1!
1'
b1 -
#3370000000
0!
0'
#3375000000
1!
1'
b10 -
#3380000000
0!
0'
#3385000000
1!
1'
b11 -
10
#3390000000
0!
0'
#3395000000
1!
1'
b0 -
00
#3400000000
0!
0'
#3405000000
1!
1'
b1 -
#3410000000
0!
0'
#3415000000
1!
1'
b10 -
#3420000000
0!
0'
#3425000000
1!
1'
b11 -
10
#3430000000
0!
0'
#3435000000
1!
1'
b0 -
00
#3440000000
0!
0'
#3445000000
1!
1'
b1 -
#3450000000
0!
0'
#3455000000
1!
1'
b10 -
#3460000000
0!
0'
#3465000000
1!
1'
b11 -
10
#3470000000
0!
0'
#3475000000
1!
1'
b0 -
00
#3480000000
0!
0'
#3485000000
1!
1'
b1 -
#3490000000
0!
0'
#3495000000
1!
1'
b10 -
#3500000000
0!
0'
#3505000000
1!
1'
b11 -
10
#3510000000
0!
0'
#3515000000
1!
1'
b0 -
00
#3520000000
0!
0'
#3525000000
1!
1'
b1 -
#3530000000
0!
0'
#3535000000
1!
1'
b10 -
#3540000000
0!
0'
#3545000000
1!
1'
b11 -
10
#3550000000
0!
0'
#3555000000
1!
1'
b0 -
00
#3560000000
0!
0'
#3565000000
1!
1'
b1 -
#3570000000
0!
0'
#3575000000
1!
1'
b10 -
#3580000000
0!
0'
#3585000000
1!
1'
b11 -
10
#3590000000
0!
0'
#3595000000
1!
1'
b0 -
00
#3600000000
0!
0'
#3605000000
1!
1'
b1 -
#3610000000
0!
0'
#3615000000
1!
1'
b10 -
#3620000000
0!
0'
#3625000000
1!
1'
b11 -
10
#3630000000
0!
0'
#3635000000
1!
1'
b0 -
00
#3640000000
0!
0'
#3645000000
1!
1'
b1 -
#3650000000
0!
0'
#3655000000
1!
1'
b10 -
#3660000000
0!
0'
#3665000000
1!
1'
b11 -
10
#3670000000
0!
0'
#3675000000
1!
1'
b0 -
00
#3680000000
0!
0'
#3685000000
1!
1'
b1 -
#3690000000
0!
0'
#3695000000
1!
1'
b10 -
#3700000000
0!
0'
#3705000000
1!
1'
b11 -
10
#3710000000
0!
0'
#3715000000
1!
1'
b0 -
00
#3720000000
0!
0'
#3725000000
1!
1'
b1 -
#3730000000
0!
0'
#3735000000
1!
1'
b10 -
#3740000000
0!
0'
#3745000000
1!
1'
b11 -
10
